sphinx_external_toc_strict/__init__.py
sphinx_external_toc_strict/__init__.pyi
sphinx_external_toc_strict/_compat.py
sphinx_external_toc_strict/_version.py
sphinx_external_toc_strict/_version.pyi
sphinx_external_toc_strict/api.py
sphinx_external_toc_strict/api.pyi
sphinx_external_toc_strict/cli.py
sphinx_external_toc_strict/cli.pyi
sphinx_external_toc_strict/constants.py
sphinx_external_toc_strict/constants.pyi
sphinx_external_toc_strict/events.py
sphinx_external_toc_strict/events.pyi
sphinx_external_toc_strict/exceptions.py
sphinx_external_toc_strict/exceptions.pyi
sphinx_external_toc_strict/filename_suffix.py
sphinx_external_toc_strict/filename_suffix.pyi
sphinx_external_toc_strict/parsing_shared.py
sphinx_external_toc_strict/parsing_shared.pyi
sphinx_external_toc_strict/parsing_strictyaml.py
sphinx_external_toc_strict/parsing_strictyaml.pyi
sphinx_external_toc_strict/pep518_read.py
sphinx_external_toc_strict/pep518_read.pyi
sphinx_external_toc_strict/py.typed
sphinx_external_toc_strict/sphinx_node.py
sphinx_external_toc_strict/sphinx_node.pyi
sphinx_external_toc_strict/tools_strictyaml.py
sphinx_external_toc_strict/tools_strictyaml.pyi
sphinx_external_toc_strict/version_semantic.py
sphinx_external_toc_strict/version_semantic.pyi
sphinx_external_toc_strict-2.0.3.post5.dist-info/licenses/LICENSE
sphinx_external_toc_strict-2.0.3.post5.dist-info/licenses/NOTICE.txt
sphinx_external_toc_strict-2.0.3.post5.dist-info/METADATA
sphinx_external_toc_strict-2.0.3.post5.dist-info/WHEEL
sphinx_external_toc_strict-2.0.3.post5.dist-info/entry_points.txt
sphinx_external_toc_strict-2.0.3.post5.dist-info/top_level.txt
sphinx_external_toc_strict-2.0.3.post5.dist-info/RECORD
